{"flavor": "Totemsmiths like to use the rarest woods for their totems.  There are even rumors of totems made of Ironbark Protectors.", "playerClass": "Shaman", "img": "http://wow.zamimg.com/images/hearthstone/cards/enus/original/EX1_565.png", "attack": 0, "imgGold": "http://wow.zamimg.com/images/hearthstone/cards/enus/animated/EX1_565_premium.gif", "health": 3, "race": "Totem", "locale": "enUS", "rarity": "Free", "text": "Adjacent minions have +2 Attack.", "faction": "Neutral", "howToGet": "Unlocked at Level 4.", "howToGetGold": "Unlocked at Level 43.", "type": "Minion", "cardSet": "Basic", "name": "Flametongue Totem", "mechanics": [{"name": "AdjacentBuff"}, {"name": "Aura"}], "collectible": true, "sounds": "//wow.zamimg.com/hearthhead/sounds/EX1_565_Play_FlametongueTotem.ogg", "cost": 2, "artist": "Jonathan Ryder", "cardId": "EX1_565"}