{"flavor": "Druids who fought too long in Northrend were easily seduced by Ragnaros; a mug of hot chocolate was generally all it took.", "howToGetGold": "Crafting unlocked in Molten Core, in the Blackrock Mountain adventure.", "type": "Minion", "cardSet": "Blackrock Mountain", "playerClass": "Druid", "img": "http://wow.zamimg.com/images/hearthstone/cards/enus/original/BRM_010.png", "attack": 2, "name": "Druid of the Flame", "imgGold": "http://wow.zamimg.com/images/hearthstone/cards/enus/animated/BRM_010_premium.gif", "health": 2, "sounds": "//wow.zamimg.com/hearthhead/sounds/VO_BRM_010_Play_01.ogg", "collectible": true, "locale": "enUS", "rarity": "Common", "howToGet": "Unlocked in Molten Core, in the Blackrock Mountain adventure.", "cost": 3, "text": "<b>Choose One</b> - Transform into a 5/2 minion; or a 2/5 minion.", "artist": "Stanley Lau", "cardId": "BRM_010"}