{"flavor": "If you hit an Eredar Lord with enough Wisps, it will explode.   But why?", "type": "Minion", "cardSet": "Classic", "img": "http://wow.zamimg.com/images/hearthstone/cards/enus/original/CS2_231.png", "attack": 1, "name": "Wisp", "imgGold": "http://wow.zamimg.com/images/hearthstone/cards/enus/animated/CS2_231_premium.gif", "health": 1, "collectible": true, "locale": "enUS", "rarity": "Common", "sounds": "//wow.zamimg.com/hearthhead/sounds/CS2_231_Wisp_EnterPlay1.ogg", "cost": 0, "faction": "Neutral", "artist": "Malcolm Davis", "cardId": "CS2_231"}