{"flavor": "Warning: Do not expose to direct sunlight.", "howToGetGold": "Crafting unlocked in the Temple of Orsis, in the League of Explorers adventure.", "type": "Minion", "cardSet": "The League of Explorers", "img": "http://wow.zamimg.com/images/hearthstone/cards/enus/original/LOE_110.png", "attack": 7, "name": "Ancient Shade", "locale": "enUS", "imgGold": "http://wow.zamimg.com/images/hearthstone/cards/enus/animated/LOE_110_premium.gif", "health": 4, "sounds": "//wow.zamimg.com/hearthhead/sounds/VO_LOE_110_Play_01.ogg", "collectible": true, "mechanics": [{"name": "Battlecry"}], "rarity": "Rare", "howToGet": "Unlocked in the Temple of Orsis, in the League of Explorers adventure.", "cost": 4, "text": "<b>Battlecry:</b> Shuffle an 'Ancient Curse' into your deck that deals 7 damage to you when drawn.", "artist": "Slawomir Maniak", "cardId": "LOE_110"}