{"flavor": "Adorable.  Immune to Magic.  Doesn't pee on the rug.  The perfect pet!", "type": "Minion", "cardSet": "Classic", "img": "http://wow.zamimg.com/images/hearthstone/cards/enus/original/NEW1_023.png", "attack": 3, "name": "Faerie Dragon", "imgGold": "http://wow.zamimg.com/images/hearthstone/cards/enus/animated/NEW1_023_premium.gif", "locale": "enUS", "race": "Dragon", "collectible": true, "health": 2, "rarity": "Common", "sounds": "//wow.zamimg.com/hearthhead/sounds/NEW1_023_Faerie_Dragon_EnterPlay_2.ogg", "cost": 2, "text": "Can't be targeted by spells or Hero Powers.", "artist": "Samwise", "cardId": "NEW1_023"}