{"flavor": "He's almost been right so many times. He was <i>sure</i> it was coming during the Cataclysm.", "type": "Minion", "cardSet": "Classic", "img": "http://wow.zamimg.com/images/hearthstone/cards/enus/original/NEW1_021.png", "attack": 0, "name": "Doomsayer", "imgGold": "http://wow.zamimg.com/images/hearthstone/cards/enus/animated/NEW1_021_premium.gif", "health": 7, "collectible": true, "locale": "enUS", "rarity": "Epic", "sounds": "//wow.zamimg.com/hearthhead/sounds/VO_NEW1_021_Play_01.ogg", "cost": 2, "text": "At the start of your turn, destroy ALL minions.", "artist": "Alex Horley Orlandelli", "cardId": "NEW1_021"}