{"flavor": "\"Four out of three orcs struggle with math.\" - Angry Zurge", "type": "Minion", "cardSet": "The Grand Tournament", "playerClass": "Warrior", "img": "http://wow.zamimg.com/images/hearthstone/cards/enus/original/AT_066.png", "attack": 3, "name": "Orgrimmar Aspirant", "locale": "enUS", "imgGold": "http://wow.zamimg.com/images/hearthstone/cards/enus/animated/AT_066_premium.gif", "health": 3, "collectible": true, "mechanics": [{"name": "Inspire"}], "rarity": "Common", "sounds": "//wow.zamimg.com/hearthhead/sounds/VO_AT_066_PLAY_01.ogg", "cost": 3, "text": "<b>Inspire:</b> Give your weapon +1 Attack.", "artist": "Hideaki Takamura", "cardId": "AT_066"}