{"flavor": "His dreams of flying and breathing fire like his idol will never be realized.", "howToGetGold": "Unlocked at Druid Level 51.", "type": "Minion", "cardSet": "Basic", "img": "http://wow.zamimg.com/images/hearthstone/cards/enus/original/CS2_119.png", "attack": 2, "name": "Oasis Snapjaw", "imgGold": "http://wow.zamimg.com/images/hearthstone/cards/enus/animated/CS2_119_premium.gif", "locale": "enUS", "race": "Beast", "collectible": true, "health": 7, "rarity": "Free", "sounds": "//wow.zamimg.com/hearthhead/sounds/CS2_119_Oasis_Snapjaw_EnterPlay2.ogg", "cost": 4, "artist": "Ittoku", "cardId": "CS2_119"}